amazeme/__init__.py
amazeme/__main__.py
amazeme/amazeme.py
amazeme-1.0.1.dist-info/LICENSE
amazeme-1.0.1.dist-info/METADATA
amazeme-1.0.1.dist-info/WHEEL
amazeme-1.0.1.dist-info/entry_points.txt
amazeme-1.0.1.dist-info/top_level.txt
amazeme-1.0.1.dist-info/RECORD
