Metadata-Version: 2.1
Name: amazeme
Version: 1.0.1
Summary: CLI utilite for generating and displaying mazes in the terminal
Home-page: https://github.com/zabojeb/amazeme
Author: zabojeb
Author-email: zabojeb@bk.ru
License: MIT
Classifier: Development Status :: 5 - Production/Stable
Classifier: Intended Audience :: Developers
Classifier: License :: OSI Approved :: MIT License
Classifier: Programming Language :: Python :: 3
Classifier: Programming Language :: Python :: 3.6
Classifier: Programming Language :: Python :: 3.7
Classifier: Programming Language :: Python :: 3.8
Classifier: Programming Language :: Python :: 3.9
Classifier: Programming Language :: Python :: 3.10
Classifier: Topic :: Software Development :: Libraries :: Python Modules
Classifier: Topic :: Games/Entertainment :: Puzzle Games
Requires-Python: >=3.6
License-File: LICENSE
Requires-Dist: click
